formatted_join.py
formatted_join-1.1.2.dist-info/METADATA
formatted_join-1.1.2.dist-info/WHEEL
formatted_join-1.1.2.dist-info/licenses/LICENSE
formatted_join-1.1.2.dist-info/RECORD
